{
  "annotations": {
    "list": [
      {
        "builtIn": 1,
        "datasource": {
          "type": "grafana",
          "uid": "-- Grafana --"
        },
        "enable": true,
        "hide": true,
        "iconColor": "rgba(0, 211, 255, 1)",
        "name": "Annotations & Alerts",
        "target": {
          "limit": 100,
          "matchAny": false,
          "tags": [],
          "type": "dashboard"
        },
        "type": "dashboard"
      },
      {
        "datasource": {
          "type": "prometheus",
          "uid": "${datasource}"
        },
        "enable": true,
        "expr": "idrac_sel_entry{job=\"$job\", instance=~\"$instance\"} * 1000 < ${__to} and \nidrac_sel_entry{job=\"$job\", instance=~\"$instance\"} * 1000 > ${__from}",
        "iconColor": "purple",
        "name": "SEL",
        "tagKeys": "instance,component,severity",
        "textFormat": "{{ message }}",
        "titleFormat": "{{id}}:{{ component }}",
        "useValueForTime": "on"
      }
    ]
  },
  "editable": true,
  "fiscalYearStartMonth": 0,
  "graphTooltip": 0,
  "id": 56,
  "links": [
    {
      "asDropdown": false,
      "icon": "dashboard",
      "includeVars": false,
      "keepTime": true,
      "tags": [],
      "targetBlank": false,
      "title": "BMC overview",
      "tooltip": "",
      "type": "link",
      "url": "d/3faidY24k"
    }
  ],
  "liveNow": false,
  "panels": [
    {
      "collapsed": false,
      "gridPos": {
        "h": 1,
        "w": 24,
        "x": 0,
        "y": 0
      },
      "id": 2,
      "panels": [],
      "title": "Information",
      "type": "row"
    },
    {
      "datasource": {
        "type": "prometheus",
        "uid": "${datasource}"
      },
      "fieldConfig": {
        "defaults": {
          "mappings": [
            {
              "options": {
                "match": "null",
                "result": {
                  "text": "N/A"
                }
              },
              "type": "special"
            }
          ],
          "thresholds": {
            "mode": "absolute",
            "steps": [
              {
                "color": "green",
                "value": null
              }
            ]
          },
          "unit": "none"
        },
        "overrides": []
      },
      "gridPos": {
        "h": 2,
        "w": 4,
        "x": 0,
        "y": 1
      },
      "hideTimeOverride": true,
      "id": 4,
      "links": [],
      "options": {
        "colorMode": "value",
        "graphMode": "none",
        "justifyMode": "auto",
        "orientation": "horizontal",
        "reduceOptions": {
          "calcs": [
            "lastNotNull"
          ],
          "fields": "/^manufacturer$/",
          "values": false
        },
        "text": {},
        "textMode": "value"
      },
      "pluginVersion": "9.3.2",
      "targets": [
        {
          "alias": "",
          "bucketAggs": [
            {
              "field": "@timestamp",
              "id": "2",
              "settings": {
                "interval": "auto"
              },
              "type": "date_histogram"
            }
          ],
          "datasource": {
            "type": "prometheus",
            "uid": "${datasource}"
          },
          "editorMode": "code",
          "exemplar": false,
          "expr": "idrac_system_machine_info{instance=\"$instance\", job=\"$job\"}",
          "format": "table",
          "instant": true,
          "legendFormat": "{{manufacturer}}",
          "metrics": [
            {
              "id": "1",
              "type": "count"
            }
          ],
          "query": "",
          "range": false,
          "refId": "A",
          "timeField": "@timestamp"
        }
      ],
      "title": "Vendor",
      "type": "stat"
    },
    {
      "datasource": {
        "type": "datasource",
        "uid": "-- Dashboard --"
      },
      "fieldConfig": {
        "defaults": {
          "mappings": [
            {
              "options": {
                "match": "null",
                "result": {
                  "text": "N/A"
                }
              },
              "type": "special"
            }
          ],
          "thresholds": {
            "mode": "absolute",
            "steps": [
              {
                "color": "green",
                "value": null
              }
            ]
          },
          "unit": "none"
        },
        "overrides": []
      },
      "gridPos": {
        "h": 2,
        "w": 4,
        "x": 4,
        "y": 1
      },
      "hideTimeOverride": true,
      "id": 6,
      "links": [],
      "options": {
        "colorMode": "value",
        "graphMode": "none",
        "justifyMode": "auto",
        "orientation": "horizontal",
        "reduceOptions": {
          "calcs": [
            "lastNotNull"
          ],
          "fields": "/^serial$/",
          "values": false
        },
        "text": {},
        "textMode": "value"
      },
      "pluginVersion": "9.3.2",
      "targets": [
        {
          "datasource": {
            "type": "datasource",
            "uid": "-- Dashboard --"
          },
          "panelId": 4,
          "refId": "A"
        }
      ],
      "title": "Serial Number",
      "type": "stat"
    },
    {
      "datasource": {
        "type": "prometheus",
        "uid": "${datasource}"
      },
      "fieldConfig": {
        "defaults": {
          "mappings": [],
          "thresholds": {
            "mode": "absolute",
            "steps": [
              {
                "color": "green",
                "value": null
              }
            ]
          },
          "unit": "bytes"
        },
        "overrides": []
      },
      "gridPos": {
        "h": 2,
        "w": 4,
        "x": 8,
        "y": 1
      },
      "hideTimeOverride": true,
      "id": 20,
      "interval": "1m",
      "links": [],
      "maxDataPoints": 1,
      "options": {
        "colorMode": "value",
        "graphMode": "none",
        "justifyMode": "auto",
        "orientation": "horizontal",
        "reduceOptions": {
          "calcs": [
            "last"
          ],
          "fields": "",
          "values": false
        },
        "text": {},
        "textMode": "value"
      },
      "pluginVersion": "9.3.2",
      "targets": [
        {
          "alias": "",
          "bucketAggs": [
            {
              "field": "@timestamp",
              "id": "2",
              "settings": {
                "interval": "auto"
              },
              "type": "date_histogram"
            }
          ],
          "datasource": {
            "type": "prometheus",
            "uid": "${datasource}"
          },
          "editorMode": "code",
          "exemplar": false,
          "expr": "idrac_system_memory_size_bytes{instance=\"$instance\", job=\"$job\"}",
          "format": "time_series",
          "instant": true,
          "interval": "",
          "legendFormat": "",
          "metrics": [
            {
              "id": "1",
              "type": "count"
            }
          ],
          "query": "",
          "range": false,
          "refId": "A",
          "timeField": "@timestamp"
        }
      ],
      "timeFrom": "1m",
      "title": "Memory Size",
      "type": "stat"
    },
    {
      "datasource": {
        "type": "prometheus",
        "uid": "${datasource}"
      },
      "fieldConfig": {
        "defaults": {
          "mappings": [
            {
              "options": {
                "match": "null",
                "result": {
                  "text": "N/A"
                }
              },
              "type": "special"
            }
          ],
          "thresholds": {
            "mode": "absolute",
            "steps": [
              {
                "color": "green",
                "value": null
              },
              {
                "color": "green",
                "value": 0
              },
              {
                "color": "yellow",
                "value": 1
              },
              {
                "color": "red",
                "value": 2
              }
            ]
          },
          "unit": "none"
        },
        "overrides": []
      },
      "gridPos": {
        "h": 4,
        "w": 4,
        "x": 12,
        "y": 1
      },
      "hideTimeOverride": true,
      "id": 8,
      "interval": "1m",
      "links": [],
      "maxDataPoints": 1,
      "options": {
        "colorMode": "value",
        "graphMode": "none",
        "justifyMode": "auto",
        "orientation": "horizontal",
        "reduceOptions": {
          "calcs": [
            "lastNotNull"
          ],
          "fields": "",
          "values": false
        },
        "text": {},
        "textMode": "name"
      },
      "pluginVersion": "9.3.2",
      "targets": [
        {
          "alias": "",
          "bucketAggs": [
            {
              "field": "@timestamp",
              "id": "2",
              "settings": {
                "interval": "auto"
              },
              "type": "date_histogram"
            }
          ],
          "datasource": {
            "type": "prometheus",
            "uid": "${datasource}"
          },
          "editorMode": "code",
          "exemplar": false,
          "expr": "idrac_system_health{instance=~\"$instance\", job=\"$job\"}",
          "instant": true,
          "legendFormat": "{{status}}",
          "metrics": [
            {
              "id": "1",
              "type": "count"
            }
          ],
          "query": "",
          "range": false,
          "refId": "A",
          "timeField": "@timestamp"
        }
      ],
      "timeFrom": "1m",
      "title": "Health",
      "type": "stat"
    },
    {
      "datasource": {
        "type": "prometheus",
        "uid": "${datasource}"
      },
      "fieldConfig": {
        "defaults": {
          "mappings": [
            {
              "options": {
                "0": {
                  "color": "red",
                  "index": 1,
                  "text": "Off"
                },
                "1": {
                  "color": "green",
                  "index": 0,
                  "text": "On"
                }
              },
              "type": "value"
            }
          ],
          "thresholds": {
            "mode": "absolute",
            "steps": [
              {
                "color": "green",
                "value": null
              }
            ]
          },
          "unit": "none"
        },
        "overrides": []
      },
      "gridPos": {
        "h": 4,
        "w": 4,
        "x": 16,
        "y": 1
      },
      "hideTimeOverride": true,
      "id": 9,
      "interval": "1m",
      "links": [],
      "maxDataPoints": 1,
      "options": {
        "colorMode": "value",
        "graphMode": "none",
        "justifyMode": "auto",
        "orientation": "horizontal",
        "reduceOptions": {
          "calcs": [
            "last"
          ],
          "fields": "",
          "values": false
        },
        "text": {},
        "textMode": "value"
      },
      "pluginVersion": "9.3.2",
      "targets": [
        {
          "alias": "",
          "bucketAggs": [
            {
              "field": "@timestamp",
              "id": "2",
              "settings": {
                "interval": "auto"
              },
              "type": "date_histogram"
            }
          ],
          "datasource": {
            "type": "prometheus",
            "uid": "${datasource}"
          },
          "editorMode": "code",
          "exemplar": false,
          "expr": "idrac_system_power_on{instance=\"$instance\", job=\"$job\"}",
          "instant": true,
          "legendFormat": "",
          "metrics": [
            {
              "id": "1",
              "type": "count"
            }
          ],
          "query": "",
          "range": false,
          "refId": "A",
          "timeField": "@timestamp"
        }
      ],
      "timeFrom": "1m",
      "title": "Power Status",
      "type": "stat"
    },
    {
      "datasource": {
        "type": "prometheus",
        "uid": "${datasource}"
      },
      "fieldConfig": {
        "defaults": {
          "mappings": [
            {
              "options": {
                "match": "null",
                "result": {
                  "text": "N/A"
                }
              },
              "type": "special"
            }
          ],
          "thresholds": {
            "mode": "absolute",
            "steps": [
              {
                "color": "green",
                "value": null
              }
            ]
          },
          "unit": "none"
        },
        "overrides": []
      },
      "gridPos": {
        "h": 4,
        "w": 4,
        "x": 20,
        "y": 1
      },
      "hideTimeOverride": true,
      "id": 25,
      "interval": "1m",
      "links": [],
      "maxDataPoints": 1,
      "options": {
        "colorMode": "value",
        "graphMode": "none",
        "justifyMode": "auto",
        "orientation": "horizontal",
        "reduceOptions": {
          "calcs": [
            "lastNotNull"
          ],
          "fields": "",
          "values": false
        },
        "text": {},
        "textMode": "name"
      },
      "pluginVersion": "9.3.2",
      "targets": [
        {
          "alias": "",
          "bucketAggs": [
            {
              "field": "@timestamp",
              "id": "2",
              "settings": {
                "interval": "auto"
              },
              "type": "date_histogram"
            }
          ],
          "datasource": {
            "type": "prometheus",
            "uid": "${datasource}"
          },
          "editorMode": "code",
          "exemplar": false,
          "expr": "idrac_system_indicator_led_on{instance=\"$instance\", job=\"$job\"}",
          "instant": true,
          "legendFormat": "{{state}}",
          "metrics": [
            {
              "id": "1",
              "type": "count"
            }
          ],
          "query": "",
          "range": false,
          "refId": "A",
          "timeField": "@timestamp"
        }
      ],
      "timeFrom": "1m",
      "title": "Indicator LED",
      "type": "stat"
    },
    {
      "datasource": {
        "type": "datasource",
        "uid": "-- Dashboard --"
      },
      "fieldConfig": {
        "defaults": {
          "mappings": [
            {
              "options": {
                "match": "null",
                "result": {
                  "text": "N/A"
                }
              },
              "type": "special"
            }
          ],
          "thresholds": {
            "mode": "absolute",
            "steps": [
              {
                "color": "green",
                "value": null
              }
            ]
          },
          "unit": "none"
        },
        "overrides": []
      },
      "gridPos": {
        "h": 2,
        "w": 4,
        "x": 0,
        "y": 3
      },
      "hideTimeOverride": true,
      "id": 5,
      "links": [],
      "options": {
        "colorMode": "value",
        "graphMode": "none",
        "justifyMode": "auto",
        "orientation": "horizontal",
        "reduceOptions": {
          "calcs": [
            "lastNotNull"
          ],
          "fields": "/^model$/",
          "values": false
        },
        "text": {},
        "textMode": "value"
      },
      "pluginVersion": "9.3.2",
      "targets": [
        {
          "datasource": {
            "type": "datasource",
            "uid": "-- Dashboard --"
          },
          "panelId": 4,
          "refId": "A"
        }
      ],
      "title": "Model",
      "type": "stat"
    },
    {
      "datasource": {
        "type": "datasource",
        "uid": "-- Dashboard --"
      },
      "fieldConfig": {
        "defaults": {
          "mappings": [
            {
              "options": {
                "match": "null",
                "result": {
                  "text": "N/A"
                }
              },
              "type": "special"
            }
          ],
          "thresholds": {
            "mode": "absolute",
            "steps": [
              {
                "color": "green",
                "value": null
              }
            ]
          },
          "unit": "none"
        },
        "overrides": []
      },
      "gridPos": {
        "h": 2,
        "w": 4,
        "x": 4,
        "y": 3
      },
      "hideTimeOverride": true,
      "id": 7,
      "links": [],
      "options": {
        "colorMode": "value",
        "graphMode": "none",
        "justifyMode": "auto",
        "orientation": "horizontal",
        "reduceOptions": {
          "calcs": [
            "lastNotNull"
          ],
          "fields": "/^sku$/",
          "values": false
        },
        "text": {},
        "textMode": "value"
      },
      "pluginVersion": "9.3.2",
      "targets": [
        {
          "datasource": {
            "type": "datasource",
            "uid": "-- Dashboard --"
          },
          "panelId": 4,
          "refId": "A"
        }
      ],
      "title": "SKU",
      "type": "stat"
    },
    {
      "datasource": {
        "type": "prometheus",
        "uid": "${datasource}"
      },
      "fieldConfig": {
        "defaults": {
          "mappings": [],
          "thresholds": {
            "mode": "absolute",
            "steps": [
              {
                "color": "green",
                "value": null
              }
            ]
          },
          "unit": "none"
        },
        "overrides": []
      },
      "gridPos": {
        "h": 2,
        "w": 4,
        "x": 8,
        "y": 3
      },
      "hideTimeOverride": true,
      "id": 21,
      "interval": "1m",
      "links": [],
      "maxDataPoints": 1,
      "options": {
        "colorMode": "value",
        "graphMode": "none",
        "justifyMode": "auto",
        "orientation": "horizontal",
        "reduceOptions": {
          "calcs": [
            "last"
          ],
          "fields": "",
          "values": false
        },
        "text": {},
        "textMode": "value"
      },
      "pluginVersion": "9.3.2",
      "targets": [
        {
          "alias": "",
          "bucketAggs": [
            {
              "field": "@timestamp",
              "id": "2",
              "settings": {
                "interval": "auto"
              },
              "type": "date_histogram"
            }
          ],
          "datasource": {
            "type": "prometheus",
            "uid": "${datasource}"
          },
          "editorMode": "code",
          "exemplar": false,
          "expr": "idrac_system_cpu_count{instance=\"$instance\", job=\"$job\"}",
          "format": "time_series",
          "instant": true,
          "interval": "",
          "legendFormat": "",
          "metrics": [
            {
              "id": "1",
              "type": "count"
            }
          ],
          "query": "",
          "range": false,
          "refId": "A",
          "timeField": "@timestamp"
        }
      ],
      "timeFrom": "1m",
      "title": "CPUs",
      "type": "stat"
    },
    {
      "collapsed": false,
      "gridPos": {
        "h": 1,
        "w": 24,
        "x": 0,
        "y": 5
      },
      "id": 12,
      "panels": [],
      "title": "Sensors",
      "type": "row"
    },
    {
      "datasource": {
        "type": "prometheus",
        "uid": "${datasource}"
      },
      "fieldConfig": {
        "defaults": {
          "color": {
            "mode": "palette-classic"
          },
          "custom": {
            "axisCenteredZero": false,
            "axisColorMode": "text",
            "axisLabel": "",
            "axisPlacement": "auto",
            "barAlignment": 0,
            "drawStyle": "line",
            "fillOpacity": 10,
            "gradientMode": "opacity",
            "hideFrom": {
              "legend": false,
              "tooltip": false,
              "viz": false
            },
            "lineInterpolation": "smooth",
            "lineWidth": 1,
            "pointSize": 5,
            "scaleDistribution": {
              "type": "linear"
            },
            "showPoints": "auto",
            "spanNulls": false,
            "stacking": {
              "group": "A",
              "mode": "none"
            },
            "thresholdsStyle": {
              "mode": "off"
            }
          },
          "decimals": 0,
          "mappings": [],
          "thresholds": {
            "mode": "absolute",
            "steps": [
              {
                "color": "green",
                "value": null
              }
            ]
          },
          "unit": "celsius"
        },
        "overrides": []
      },
      "gridPos": {
        "h": 9,
        "w": 12,
        "x": 0,
        "y": 6
      },
      "id": 14,
      "options": {
        "legend": {
          "calcs": [
            "mean"
          ],
          "displayMode": "table",
          "placement": "right",
          "showLegend": true
        },
        "tooltip": {
          "mode": "multi",
          "sort": "desc"
        }
      },
      "targets": [
        {
          "alias": "",
          "bucketAggs": [
            {
              "field": "@timestamp",
              "id": "2",
              "settings": {
                "interval": "auto"
              },
              "type": "date_histogram"
            }
          ],
          "datasource": {
            "type": "prometheus",
            "uid": "${datasource}"
          },
          "editorMode": "code",
          "exemplar": false,
          "expr": "avg_over_time(idrac_sensors_temperature{instance=~\"$instance\",job=\"$job\"}[$__rate_interval])",
          "instant": false,
          "legendFormat": "{{name}}",
          "metrics": [
            {
              "id": "1",
              "type": "count"
            }
          ],
          "query": "",
          "range": true,
          "refId": "A",
          "timeField": "@timestamp"
        }
      ],
      "title": "Temperature",
      "type": "timeseries"
    },
    {
      "datasource": {
        "type": "prometheus",
        "uid": "${datasource}"
      },
      "fieldConfig": {
        "defaults": {
          "color": {
            "mode": "palette-classic"
          },
          "custom": {
            "axisCenteredZero": false,
            "axisColorMode": "text",
            "axisLabel": "",
            "axisPlacement": "auto",
            "barAlignment": 0,
            "drawStyle": "line",
            "fillOpacity": 10,
            "gradientMode": "opacity",
            "hideFrom": {
              "legend": false,
              "tooltip": false,
              "viz": false
            },
            "lineInterpolation": "smooth",
            "lineWidth": 1,
            "pointSize": 5,
            "scaleDistribution": {
              "type": "linear"
            },
            "showPoints": "auto",
            "spanNulls": false,
            "stacking": {
              "group": "A",
              "mode": "none"
            },
            "thresholdsStyle": {
              "mode": "off"
            }
          },
          "decimals": 0,
          "mappings": [],
          "thresholds": {
            "mode": "absolute",
            "steps": [
              {
                "color": "green",
                "value": null
              }
            ]
          },
          "unit": "rotrpm"
        },
        "overrides": []
      },
      "gridPos": {
        "h": 9,
        "w": 12,
        "x": 12,
        "y": 6
      },
      "id": 15,
      "options": {
        "legend": {
          "calcs": [
            "mean"
          ],
          "displayMode": "table",
          "placement": "right",
          "showLegend": true
        },
        "tooltip": {
          "mode": "multi",
          "sort": "desc"
        }
      },
      "targets": [
        {
          "alias": "",
          "bucketAggs": [
            {
              "field": "@timestamp",
              "id": "2",
              "settings": {
                "interval": "auto"
              },
              "type": "date_histogram"
            }
          ],
          "datasource": {
            "type": "prometheus",
            "uid": "${datasource}"
          },
          "editorMode": "code",
          "exemplar": false,
          "expr": "avg_over_time(idrac_sensors_fan_speed{instance=~\"$instance\",job=\"$job\"}[$__rate_interval])",
          "instant": false,
          "legendFormat": "{{name}}",
          "metrics": [
            {
              "id": "1",
              "type": "count"
            }
          ],
          "query": "",
          "range": true,
          "refId": "A",
          "timeField": "@timestamp"
        }
      ],
      "title": "Fans",
      "type": "timeseries"
    },
    {
      "collapsed": false,
      "gridPos": {
        "h": 1,
        "w": 24,
        "x": 0,
        "y": 15
      },
      "id": 17,
      "panels": [],
      "title": "Power",
      "type": "row"
    },
    {
      "datasource": {
        "type": "prometheus",
        "uid": "${datasource}"
      },
      "fieldConfig": {
        "defaults": {
          "color": {
            "mode": "palette-classic"
          },
          "custom": {
            "axisCenteredZero": true,
            "axisColorMode": "text",
            "axisLabel": "In/Out",
            "axisPlacement": "auto",
            "barAlignment": 0,
            "drawStyle": "line",
            "fillOpacity": 10,
            "gradientMode": "opacity",
            "hideFrom": {
              "legend": false,
              "tooltip": false,
              "viz": false
            },
            "lineInterpolation": "smooth",
            "lineWidth": 1,
            "pointSize": 5,
            "scaleDistribution": {
              "type": "linear"
            },
            "showPoints": "auto",
            "spanNulls": false,
            "stacking": {
              "group": "A",
              "mode": "none"
            },
            "thresholdsStyle": {
              "mode": "off"
            }
          },
          "mappings": [],
          "thresholds": {
            "mode": "absolute",
            "steps": [
              {
                "color": "green",
                "value": null
              }
            ]
          },
          "unit": "watt"
        },
        "overrides": [
          {
            "matcher": {
              "id": "byRegexp",
              "options": ".*Input.*"
            },
            "properties": [
              {
                "id": "custom.transform",
                "value": "negative-Y"
              }
            ]
          }
        ]
      },
      "gridPos": {
        "h": 8,
        "w": 11,
        "x": 0,
        "y": 16
      },
      "id": 19,
      "options": {
        "legend": {
          "calcs": [
            "mean"
          ],
          "displayMode": "table",
          "placement": "right",
          "showLegend": true
        },
        "tooltip": {
          "mode": "multi",
          "sort": "desc"
        }
      },
      "targets": [
        {
          "alias": "",
          "bucketAggs": [
            {
              "field": "@timestamp",
              "id": "2",
              "settings": {
                "interval": "auto"
              },
              "type": "date_histogram"
            }
          ],
          "datasource": {
            "type": "prometheus",
            "uid": "${datasource}"
          },
          "editorMode": "code",
          "expr": "avg_over_time(idrac_power_supply_output_watts{instance=~\"$instance\",job=\"$job\"}[$__rate_interval])",
          "legendFormat": "Output PSU-{{psu}}",
          "metrics": [
            {
              "id": "1",
              "type": "count"
            }
          ],
          "query": "",
          "range": true,
          "refId": "A",
          "timeField": "@timestamp"
        },
        {
          "datasource": {
            "type": "prometheus",
            "uid": "${datasource}"
          },
          "editorMode": "code",
          "expr": "avg_over_time(idrac_power_supply_input_watts{instance=~\"$instance\",job=\"$job\"}[$__rate_interval])",
          "hide": false,
          "legendFormat": "Input PSU-{{psu}}",
          "range": true,
          "refId": "B"
        }
      ],
      "title": "Power Supplies",
      "type": "timeseries"
    },
    {
      "datasource": {
        "type": "prometheus",
        "uid": "${datasource}"
      },
      "fieldConfig": {
        "defaults": {
          "mappings": [],
          "thresholds": {
            "mode": "absolute",
            "steps": [
              {
                "color": "green",
                "value": null
              }
            ]
          },
          "unit": "volt"
        },
        "overrides": []
      },
      "gridPos": {
        "h": 4,
        "w": 2,
        "x": 11,
        "y": 16
      },
      "hideTimeOverride": true,
      "id": 23,
      "interval": "1m",
      "links": [],
      "maxDataPoints": 1,
      "options": {
        "colorMode": "value",
        "graphMode": "none",
        "justifyMode": "auto",
        "orientation": "horizontal",
        "reduceOptions": {
          "calcs": [
            "last"
          ],
          "fields": "",
          "values": false
        },
        "text": {},
        "textMode": "value"
      },
      "pluginVersion": "9.3.2",
      "targets": [
        {
          "alias": "",
          "bucketAggs": [
            {
              "field": "@timestamp",
              "id": "2",
              "settings": {
                "interval": "auto"
              },
              "type": "date_histogram"
            }
          ],
          "datasource": {
            "type": "prometheus",
            "uid": "${datasource}"
          },
          "editorMode": "code",
          "exemplar": false,
          "expr": "avg(idrac_power_supply_input_voltage{instance=~\"$instance\", job=\"$job\"})",
          "format": "time_series",
          "instant": true,
          "interval": "",
          "legendFormat": "",
          "metrics": [
            {
              "id": "1",
              "type": "count"
            }
          ],
          "query": "",
          "range": false,
          "refId": "A",
          "timeField": "@timestamp"
        }
      ],
      "timeFrom": "1m",
      "title": "Voltage",
      "type": "stat"
    },
    {
      "datasource": {
        "type": "prometheus",
        "uid": "${datasource}"
      },
      "fieldConfig": {
        "defaults": {
          "color": {
            "mode": "palette-classic"
          },
          "custom": {
            "axisCenteredZero": false,
            "axisColorMode": "text",
            "axisLabel": "",
            "axisPlacement": "auto",
            "barAlignment": 0,
            "drawStyle": "line",
            "fillOpacity": 10,
            "gradientMode": "opacity",
            "hideFrom": {
              "legend": false,
              "tooltip": false,
              "viz": false
            },
            "lineInterpolation": "smooth",
            "lineWidth": 1,
            "pointSize": 5,
            "scaleDistribution": {
              "type": "linear"
            },
            "showPoints": "auto",
            "spanNulls": false,
            "stacking": {
              "group": "A",
              "mode": "none"
            },
            "thresholdsStyle": {
              "mode": "off"
            }
          },
          "mappings": [],
          "thresholds": {
            "mode": "absolute",
            "steps": [
              {
                "color": "green",
                "value": null
              }
            ]
          },
          "unit": "watt"
        },
        "overrides": []
      },
      "gridPos": {
        "h": 8,
        "w": 11,
        "x": 13,
        "y": 16
      },
      "id": 22,
      "options": {
        "legend": {
          "calcs": [
            "mean"
          ],
          "displayMode": "list",
          "placement": "right",
          "showLegend": false
        },
        "tooltip": {
          "mode": "multi",
          "sort": "desc"
        }
      },
      "targets": [
        {
          "alias": "",
          "bucketAggs": [
            {
              "field": "@timestamp",
              "id": "2",
              "settings": {
                "interval": "auto"
              },
              "type": "date_histogram"
            }
          ],
          "datasource": {
            "type": "prometheus",
            "uid": "${datasource}"
          },
          "editorMode": "code",
          "expr": "avg_over_time(idrac_power_control_avg_consumed_watts{instance=~\"$instance\",job=\"$job\"}[$__rate_interval])",
          "legendFormat": "{{name}}",
          "metrics": [
            {
              "id": "1",
              "type": "count"
            }
          ],
          "query": "",
          "range": true,
          "refId": "A",
          "timeField": "@timestamp"
        }
      ],
      "title": "Power Consumption",
      "type": "timeseries"
    },
    {
      "datasource": {
        "type": "prometheus",
        "uid": "${datasource}"
      },
      "fieldConfig": {
        "defaults": {
          "mappings": [],
          "thresholds": {
            "mode": "absolute",
            "steps": [
              {
                "color": "green",
                "value": null
              }
            ]
          },
          "unit": "watt"
        },
        "overrides": []
      },
      "gridPos": {
        "h": 4,
        "w": 2,
        "x": 11,
        "y": 20
      },
      "hideTimeOverride": true,
      "id": 24,
      "interval": "1m",
      "links": [],
      "maxDataPoints": 1,
      "options": {
        "colorMode": "value",
        "graphMode": "none",
        "justifyMode": "auto",
        "orientation": "horizontal",
        "reduceOptions": {
          "calcs": [
            "last"
          ],
          "fields": "",
          "values": false
        },
        "text": {},
        "textMode": "value"
      },
      "pluginVersion": "9.3.2",
      "targets": [
        {
          "alias": "",
          "bucketAggs": [
            {
              "field": "@timestamp",
              "id": "2",
              "settings": {
                "interval": "auto"
              },
              "type": "date_histogram"
            }
          ],
          "datasource": {
            "type": "prometheus",
            "uid": "${datasource}"
          },
          "editorMode": "code",
          "exemplar": false,
          "expr": "idrac_power_control_capacity_watts{id=\"0\",instance=~\"$instance\", job=\"$job\"}",
          "format": "time_series",
          "instant": true,
          "interval": "",
          "legendFormat": "",
          "metrics": [
            {
              "id": "1",
              "type": "count"
            }
          ],
          "query": "",
          "range": false,
          "refId": "A",
          "timeField": "@timestamp"
        }
      ],
      "timeFrom": "1m",
      "title": "Capacity",
      "type": "stat"
    },
    {
      "collapsed": false,
      "gridPos": {
        "h": 1,
        "w": 24,
        "x": 0,
        "y": 24
      },
      "id": 29,
      "panels": [],
      "title": "Event log",
      "type": "row"
    },
    {
      "datasource": {
        "type": "prometheus",
        "uid": "${datasource}"
      },
      "fieldConfig": {
        "defaults": {
          "color": {
            "mode": "thresholds"
          },
          "custom": {
            "align": "auto",
            "displayMode": "auto",
            "inspect": false
          },
          "mappings": [],
          "thresholds": {
            "mode": "absolute",
            "steps": [
              {
                "color": "green",
                "value": null
              },
              {
                "color": "red",
                "value": 80
              }
            ]
          }
        },
        "overrides": [
          {
            "matcher": {
              "id": "byName",
              "options": "Value"
            },
            "properties": [
              {
                "id": "unit",
                "value": "dateTimeAsSystem"
              }
            ]
          },
          {
            "matcher": {
              "id": "byName",
              "options": "id"
            },
            "properties": [
              {
                "id": "custom.width",
                "value": 52
              }
            ]
          },
          {
            "matcher": {
              "id": "byName",
              "options": "Time"
            },
            "properties": [
              {
                "id": "custom.width",
                "value": 168
              }
            ]
          },
          {
            "matcher": {
              "id": "byName",
              "options": "severity"
            },
            "properties": [
              {
                "id": "custom.width",
                "value": 91
              },
              {
                "id": "mappings",
                "value": [
                  {
                    "options": {
                      "Critical": {
                        "color": "red",
                        "index": 0
                      },
                      "OK": {
                        "color": "green",
                        "index": 2
                      },
                      "Warning": {
                        "color": "yellow",
                        "index": 1
                      }
                    },
                    "type": "value"
                  }
                ]
              },
              {
                "id": "custom.displayMode",
                "value": "color-text"
              }
            ]
          },
          {
            "matcher": {
              "id": "byName",
              "options": "component"
            },
            "properties": [
              {
                "id": "custom.width",
                "value": 217
              }
            ]
          },
          {
            "matcher": {
              "id": "byName",
              "options": "instance"
            },
            "properties": [
              {
                "id": "custom.width",
                "value": 103
              }
            ]
          }
        ]
      },
      "gridPos": {
        "h": 4,
        "w": 24,
        "x": 0,
        "y": 25
      },
      "id": 27,
      "options": {
        "footer": {
          "fields": "",
          "reducer": [
            "sum"
          ],
          "show": false
        },
        "showHeader": true,
        "sortBy": []
      },
      "pluginVersion": "9.3.2",
      "targets": [
        {
          "datasource": {
            "type": "prometheus",
            "uid": "${datasource}"
          },
          "editorMode": "code",
          "exemplar": false,
          "expr": "idrac_sel_entry{job=\"$job\", instance=~\"$instance\"} * 1000 < ${__to} and \nidrac_sel_entry{job=\"$job\", instance=~\"$instance\"} * 1000 > ${__from}",
          "format": "table",
          "instant": true,
          "legendFormat": "{{id}} {{component}}:  {{message}}",
          "range": false,
          "refId": "A"
        }
      ],
      "title": "System Event Log (SEL)",
      "transformations": [
        {
          "id": "convertFieldType",
          "options": {
            "conversions": [
              {
                "destinationType": "number",
                "targetField": "id"
              }
            ],
            "fields": {}
          }
        },
        {
          "id": "sortBy",
          "options": {
            "fields": {},
            "sort": [
              {
                "desc": true,
                "field": "id"
              }
            ]
          }
        },
        {
          "id": "filterFieldsByName",
          "options": {
            "include": {
              "pattern": "message|id|component|severity|Value"
            }
          }
        },
        {
          "id": "organize",
          "options": {
            "excludeByName": {},
            "indexByName": {
              "Value": 0,
              "component": 4,
              "id": 2,
              "instance": 1,
              "message": 5,
              "severity": 3
            },
            "renameByName": {
              "Value": "Time"
            }
          }
        }
      ],
      "type": "table"
    }
  ],
  "refresh": "30s",
  "schemaVersion": 37,
  "style": "dark",
  "tags": [
    "dell",
    "idrac"
  ],
  "templating": {
    "list": [
      {
        "hide": 0,
        "includeAll": false,
        "label": "Datasource",
        "multi": false,
        "name": "datasource",
        "options": [],
        "query": "prometheus",
        "queryValue": "",
        "refresh": 1,
        "regex": ".+",
        "skipUrlSync": false,
        "type": "datasource"
      },
      {
        "datasource": {
          "type": "prometheus",
          "uid": "${datasource}"
        },
        "definition": "label_values(idrac_machine_info,job)",
        "hide": 0,
        "includeAll": false,
        "multi": true,
        "name": "job",
        "options": [],
        "query": {
          "query": "label_values(idrac_machine_info,job)",
          "refId": "StandardVariableQuery"
        },
        "refresh": 1,
        "regex": "",
        "skipUrlSync": false,
        "sort": 1,
        "type": "query"
      },
      {
        "allValue": ".+",
        "datasource": {
          "type": "prometheus",
          "uid": "${datasource}"
        },
        "definition": "label_values(idrac_machine_info{job=\"$job\"}, instance)",
        "hide": 0,
        "includeAll": false,
        "label": "",
        "multi": false,
        "name": "instance",
        "options": [],
        "query": {
          "query": "label_values(idrac_machine_info{job=\"$job\"}, instance)",
          "refId": "StandardVariableQuery"
        },
        "refresh": 1,
        "regex": "",
        "skipUrlSync": false,
        "sort": 1,
        "type": "query"
      }
    ]
  },
  "time": {
    "from": "now-1h",
    "to": "now"
  },
  "timepicker": {},
  "timezone": "",
  "title": "BMC",
  "uid": "YVz226S4z",
  "version": 19,
  "weekStart": ""
}
